testforPPshare/__init__.py
testforPPshare/stock/__init__.py
testforPPshare/stock/macro/__init__.py
testforPPshare/stock/macro/bor.py
testforPPshare/stock/macro/cons.py
testforPPshare/stock/macro/demjson.py
testforPPshare/stock/macro/eastmoney.py
testforPPshare/stock/macro/func.py
testforPPshare/stock/macro/macro_australia.py
testforPPshare/stock/macro/macro_bank.py
testforPPshare/stock/macro/macro_canada.py
testforPPshare/stock/macro/macro_china.py
testforPPshare/stock/macro/macro_cnbs.py
testforPPshare/stock/macro/macro_constitute.py
testforPPshare/stock/macro/macro_euro.py
testforPPshare/stock/macro/macro_germany.py
testforPPshare/stock/macro/macro_japan.py
testforPPshare/stock/macro/macro_other.py
testforPPshare/stock/macro/macro_swiss.py
testforPPshare/stock/macro/macro_uk.py
testforPPshare/stock/macro/macro_usa.py
testforPPshare/stock/macro/shibor.py
testforPPshare/util/__init__.py
testforPPshare/util/demjson.py
testforPPshare/util/function.py
testforPPshare/util/info.xlsx
testforPPshare/util/text.py
testforPPshare-0.2.5.dist-info/LICENSE
testforPPshare-0.2.5.dist-info/METADATA
testforPPshare-0.2.5.dist-info/WHEEL
testforPPshare-0.2.5.dist-info/top_level.txt
testforPPshare-0.2.5.dist-info/RECORD
