Metadata-Version: 2.1
Name: testforPPshare
Version: 0.2.5
Summary: PPtest is a utility for crawling historical and Real-time Quotes data of marco data
Home-page: https://github.com/zemengchuan/PPtest
Author: zemengchuan
Author-email: zemengchuan@gmail.com
License: MIT
Keywords: macro,webcrawler,data
Classifier: Programming Language :: Python :: 3.7
Classifier: Programming Language :: Python :: 3.8
Classifier: Programming Language :: Python :: 3.9
Classifier: Programming Language :: Python :: 3.10
Classifier: Programming Language :: Python :: 3.11
Classifier: License :: OSI Approved :: MIT License
Classifier: Operating System :: OS Independent
Requires-Python: >=3.7
License-File: LICENSE
Requires-Dist: requests
Requires-Dist: pandas
Requires-Dist: openpyxl
Requires-Dist: python-Levenshtein
Requires-Dist: fuzzywuzzy
